rdx.py
rdx-1.1.dist-info/LICENSE
rdx-1.1.dist-info/METADATA
rdx-1.1.dist-info/WHEEL
rdx-1.1.dist-info/top_level.txt
rdx-1.1.dist-info/RECORD
